progentrl/__init__.py
progentrl/dataloader.py
progentrl/decoder.py
progentrl/encoder.py
progentrl/gen_rl.py
progentrl/gen_vaelp.py
progentrl/gentrl_old.py
progentrl/lp.py
progentrl/tokenizer.py
progentrl/utils.py
progentrl-1.0.0.dist-info/LICENSE
progentrl-1.0.0.dist-info/METADATA
progentrl-1.0.0.dist-info/WHEEL
progentrl-1.0.0.dist-info/top_level.txt
progentrl-1.0.0.dist-info/RECORD
