Metadata-Version: 2.1
Name: progentrl
Version: 1.0.0
Summary: Pro Generative Tensorial Reinforcement Learning (proGENTRL): Leverage the power using pytorch Lightning and generate molecules
Home-page: https://github.com/Bibyutatsu/proGENTRL
Author: Bibyutatsu
Author-email: bibhashm220896@gmail.com
License: MIT
Platform: UNKNOWN
Classifier: License :: OSI Approved :: MIT License
Classifier: Programming Language :: Python
Classifier: Programming Language :: Python :: 3
Classifier: Programming Language :: Python :: 3.6
Requires-Python: >=3.5.0
Requires-Dist: numpy (>=1.15)
Requires-Dist: pandas (>=0.23)
Requires-Dist: scipy (>=1.1.0)
Requires-Dist: molsets
Requires-Dist: scikit-learn (>=0.21.3)
Requires-Dist: pytorch-lightning (>=0.7.6)
Requires-Dist: joblib (>=0.13.2)
